auror/__init__.py
auror/parameter.py
auror/protego.py
auror-0.3.13.dist-info/METADATA
auror-0.3.13.dist-info/WHEEL
auror-0.3.13.dist-info/top_level.txt
auror-0.3.13.dist-info/RECORD
