Metadata-Version: 2.1
Name: auror
Version: 0.3.13
Summary: Parameter Checking
Author-email: Joshua Hoskins <jhoskins@nrao.edu>
Requires-Python: <3.12,>=3.8
Requires-Dist: cerberus
Requires-Dist: tqdm
Requires-Dist: numpy
Requires-Dist: pytest
Requires-Dist: pytest-cov
Requires-Dist: pytest-html
Requires-Dist: xarray
Provides-Extra: docs
Requires-Dist: ipykernel ; extra == 'docs'
Requires-Dist: ipympl ; extra == 'docs'
Requires-Dist: ipython ; extra == 'docs'
Requires-Dist: jupyter-client ; extra == 'docs'
Requires-Dist: nbsphinx ; extra == 'docs'
Requires-Dist: recommonmark ; extra == 'docs'
Requires-Dist: scanpydoc ; extra == 'docs'
Requires-Dist: sphinx-autoapi ; extra == 'docs'
Requires-Dist: sphinx-autosummary-accessors ; extra == 'docs'
Requires-Dist: sphinx-rtd-theme ; extra == 'docs'
Requires-Dist: twine ; extra == 'docs'
Requires-Dist: pandoc ; extra == 'docs'
